[
 {
  "no": 0,
  "eventStart": 1381196888,
  "eventEnd": 1382065997,
  "operationStart": 1381297351,
  "doOff": 1381697069,
  "tA": 32,
  "tO": 399718,
  "tR": 368928,
  "eventResult": "Success",
  "details": []
 },
 {
  "no": 1,
  "eventStart": 1386673802,
  "eventEnd": 1387477143,
  "operationStart": 1386774300,
  "doOff": 1387173903,
  "tA": 33,
  "tO": 399603,
  "tR": 303240,
  "eventResult": "Success",
  "details": []
 },
 {
  "no": 2,
  "eventStart": 1391012772,
  "eventEnd": 1391788722,
  "operationStart": 1391112863,
  "doOff": 1391512949,
  "tA": 32,
  "tO": 400086,
  "tR": 275773,
  "eventResult": "Success",
  "details": []
 },
 {
  "no": 3,
  "eventStart": 1407392175,
  "eventEnd": 1408236847,
  "operationStart": 1407492586,
  "doOff": 1407892402,
  "tA": 32,
  "tO": 399816,
  "tR": 344445,
  "eventResult": "Success",
  "details": []
 },
 {
  "no": 4,
  "eventStart": 1412754986,
  "eventEnd": 1443597296,
  "operationStart": 1412855179,
  "doOff": 1413255183,
  "tA": 31,
  "tO": 400004,
  "tR": 30342113,
  "eventResult": "Success",
  "details": []
 }
]